VL53L3CX.py
vl53l3cx_python.cpython-39-arm-linux-gnueabihf.so
vl53l3cx-1.0.1.dist-info/METADATA
vl53l3cx-1.0.1.dist-info/WHEEL
vl53l3cx-1.0.1.dist-info/top_level.txt
vl53l3cx-1.0.1.dist-info/RECORD
