Metadata-Version: 2.4
Name: VL53L3CX
Version: 1.0.1
Summary: VL53L3CX distance sensor driver for Raspberry Pi
Home-page: https://github.com/FrgyCZ/VL53L3CX-python
Maintainer: Jakub Frgal
Maintainer-email: buemicz@gmail.com
Requires-Dist: smbus2
Dynamic: description
Dynamic: description-content-type
Dynamic: home-page
Dynamic: maintainer
Dynamic: maintainer-email
Dynamic: requires-dist
Dynamic: summary
